venndata/__init__.py
venndata/venn.py
venndata-0.1.0.dist-info/LICENSE
venndata-0.1.0.dist-info/METADATA
venndata-0.1.0.dist-info/WHEEL
venndata-0.1.0.dist-info/top_level.txt
venndata-0.1.0.dist-info/RECORD
