Metadata-Version: 2.1
Name: venndata
Version: 0.1.0
Summary: Package for plotting Venn diagrams with more than 3 sets
Home-page: https://github.com/mandalsubhajit/venndata
Author: Subhajit Mandal
Author-email: mandalsubhajit@gmail.com
License: UNKNOWN
Platform: UNKNOWN
Classifier: Programming Language :: Python :: 3
Classifier: License :: OSI Approved :: MIT License
Classifier: Operating System :: OS Independent
Requires-Python: >=3.6
